coupled_cluster_py-0.0.5.dist-info/RECORD
coupled_cluster_py-0.0.5.dist-info/WHEEL
coupled_cluster_py-0.0.5.dist-info/COPYING
coupled_cluster_py-0.0.5.dist-info/METADATA
ccpy/_version.py
ccpy/__init__.py
ccpy/moments/cripcc23.py
ccpy/moments/creacc23.py
ccpy/moments/crcc34.py
ccpy/moments/crcc24.py
ccpy/moments/ccp3_chol.py
ccpy/moments/dipeomccsdta_star.py
ccpy/moments/creomcc23.py
ccpy/moments/ccp3.py
ccpy/moments/cct3.py
ccpy/moments/__init__.py
ccpy/moments/ipeomccsdta_star.py
ccpy/moments/eomccsdta_star.py
ccpy/moments/eccc23.py
ccpy/moments/creomcc23_chol.py
ccpy/moments/ccp4.py
ccpy/moments/ipccp3.py
ccpy/moments/eaccp3.py
ccpy/moments/crcc23.py
ccpy/moments/crcc23_chol.py
ccpy/moments/cct3_chol.py
ccpy/moments/eaeomccsdta_star.py
ccpy/drivers/__init__.py
ccpy/drivers/solvers.py
ccpy/drivers/adaptive.py
ccpy/drivers/driver.py
ccpy/drivers/diis.py
ccpy/energy/hf_energy.py
ccpy/energy/cc_energy.py
ccpy/energy/__init__.py
ccpy/energy/lrcc_energy.py
ccpy/mbpt/mbpt.py
ccpy/mbpt/mbgf.py
ccpy/mbpt/__init__.py
ccpy/extcorr/contractions_t4.py
ccpy/extcorr/external_correction.py
ccpy/extcorr/__init__.py
ccpy/extcorr/ecccp3.py
ccpy/extcorr/contractions_t3.py
ccpy/constants/constants.py
ccpy/constants/__init__.py
ccpy/hbar/hbar_ccsdt.py
ccpy/hbar/hbar_ccsdt1.py
ccpy/hbar/__init__.py
ccpy/hbar/hbar_cc4.py
ccpy/hbar/diagonal.py
ccpy/hbar/hbar_cc3.py
ccpy/hbar/hbar_ccsd.py
ccpy/hbar/hbar_ccsdt_p.py
ccpy/hbar/hbar_ccsdta.py
ccpy/hbar/hbar_ccs.py
ccpy/hbar/hbar_ccsd_chol.py
ccpy/eom_guess/cisd.py
ccpy/eom_guess/sfcis.py
ccpy/eom_guess/cisd_chol.py
ccpy/eom_guess/__init__.py
ccpy/eom_guess/eacis.py
ccpy/eom_guess/deacis.py
ccpy/eom_guess/cis.py
ccpy/eom_guess/s2matrix.py
ccpy/eom_guess/dipcis.py
ccpy/eom_guess/ipcis.py
ccpy/eom_guess/eacisd.py
ccpy/eom_guess/ipcisd.py
ccpy/left/left_eaeom3.py
ccpy/left/left_ipeom3.py
ccpy/left/left_ipeom2.py
ccpy/left/left_cc_intermediates.py
ccpy/left/left_eaeom2.py
ccpy/left/left_eaeom_intermediates.py
ccpy/left/__init__.py
ccpy/left/left_ccsd_chol.py
ccpy/left/left_eaeom3_p.py
ccpy/left/left_ccsd.py
ccpy/left/left_cc3.py
