Metadata-Version: 2.1
Name: coupled-cluster-py
Version: 0.0.5
Summary: Coupled-cluster package written in Python.
Author-Email: Karthik Gururangan <gururang@msu.edu>
Maintainer-Email: Karthik Gururangan <gururang@msu.edu>, Emiliano Deustua <edeustua@gmail.com>, Piotr Piecuch <piecuch@chemistry.msu.edu>
License:                     GNU GENERAL PUBLIC LICENSE
Classifier: Development Status :: 5 - Production/Stable
Classifier: Intended Audience :: Science/Research
Classifier: Intended Audience :: Developers
Classifier: License :: OSI Approved :: GNU General Public License v3 (GPLv3)
Classifier: Programming Language :: Fortran
Classifier: Programming Language :: Python
Classifier: Programming Language :: Python :: 3
Classifier: Programming Language :: Python :: 3.10
Classifier: Programming Language :: Python :: 3.11
Classifier: Programming Language :: Python :: 3.12
Classifier: Topic :: Software Development :: Libraries
Classifier: Topic :: Scientific/Engineering
Classifier: Operating System :: POSIX :: Linux
Classifier: Operating System :: POSIX
Classifier: Operating System :: Unix
Classifier: Operating System :: MacOS
Project-URL: homepage, https://piecuch-group.github.io/ccpy/
Project-URL: documentation, https://piecuch-group.github.io/ccpy/
Project-URL: source, https://github.com/piecuch-group/ccpy
Project-URL: download, https://github.com/piecuch-group/ccpy/releases
Project-URL: tracker, https://github.com/piecuch-group/ccpy/issues
Requires-Python: >=3.10
Requires-Dist: numpy>=2.0
Requires-Dist: pyscf
Requires-Dist: cclib
Requires-Dist: psutil
Provides-Extra: test
Requires-Dist: pytest; extra == "test"
Requires-Dist: meson; extra == "test"
Requires-Dist: ninja; sys_platform != "emscripten" and extra == "test"
Provides-Extra: doc
Provides-Extra: dev
Requires-Dist: ruff>=0.0.292; extra == "dev"
